[
	{
		"model": "registries.activitycode",
		"pk": "9ecb8fbb-428f-45e1-9a3f-e0ce05c563e2",
		"fields": {
			"who_created": "DATALOAD_USER",
			"when_created": "2018-01-01T08:00:00Z",
			"who_updated": "DATALOAD_USER",
			"when_updated": "2018-01-01T08:00:00Z",
			"code": "DRILL",
			"description": "Well Driller",
			"is_hidden": false,
			"sort_order": 2
		}
	},
	{
		"model": "registries.activitycode",
		"pk": "a2c5ac6f-13b6-42c5-9e91-9672ab2ef5a8",
		"fields": {
			"who_created": "DATALOAD_USER",
			"when_created": "2018-01-01T08:00:00Z",
			"who_updated": "DATALOAD_USER",
			"when_updated": "2018-01-01T08:00:00Z",
			"code": "PUMP",
			"description": "Pump Installer",
			"is_hidden": false,
			"sort_order": 4
		}
	}
]